domino_spatial/DOMINO.py
domino_spatial/__init__.py
domino_spatial/cli.py
domino_spatial/cluster.py
domino_spatial/layer.py
domino_spatial/model.py
domino_spatial/preprocess.py
domino_spatial-0.1.5.dist-info/LICENSE
domino_spatial-0.1.5.dist-info/METADATA
domino_spatial-0.1.5.dist-info/WHEEL
domino_spatial-0.1.5.dist-info/entry_points.txt
domino_spatial-0.1.5.dist-info/top_level.txt
domino_spatial-0.1.5.dist-info/RECORD
